{"total": 48, "filters": "{\"PriceArea\":[\"DK1\",\"DK2\"]}", "sort": "TimeUTC desc", "limit": 48, "dataset": "DayAheadPrices", "records": [{"TimeUTC": "2026-06-24T22:45:00", "TimeDK": "2026-06-25T00:45:00", "PriceArea": "DK1", "DayAheadPriceEUR": 152.929993, "DayAheadPriceDKK": 1143.136405}, {"TimeUTC": "2026-06-24T22:45:00", "TimeDK": "2026-06-25T00:45:00", "PriceArea": "DK2", "DayAheadPriceEUR": 153.100006, "DayAheadPriceDKK": 1144.407235}, {"TimeUTC": "2026-06-24T22:30:00", "TimeDK": "2026-06-25T00:30:00", "PriceArea": "DK1", "DayAheadPriceEUR": 153.970001, "DayAheadPriceDKK": 1150.91036}, {"TimeUTC": "2026-06-24T22:30:00", "TimeDK": "2026-06-25T00:30:00", "PriceArea": "DK2", "DayAheadPriceEUR": 154.020004, "DayAheadPriceDKK": 1151.284128}, {"TimeUTC": "2026-06-24T22:15:00", "TimeDK": "2026-06-25T00:15:00", "PriceArea": "DK1", "DayAheadPriceEUR": 171.0, "DayAheadPriceDKK": 1278.2079}, {"TimeUTC": "2026-06-24T22:15:00", "TimeDK": "2026-06-25T00:15:00", "PriceArea": "DK2", "DayAheadPriceEUR": 171.009995, "DayAheadPriceDKK": 1278.282612}, {"TimeUTC": "2026-06-24T22:00:00", "TimeDK": "2026-06-25T00:00:00", "PriceArea": "DK1", "DayAheadPriceEUR": 200.100006, "DayAheadPriceDKK": 1495.727535}, {"TimeUTC": "2026-06-24T22:00:00", "TimeDK": "2026-06-25T00:00:00", "PriceArea": "DK2", "DayAheadPriceEUR": 200.100006, "DayAheadPriceDKK": 1495.727535}, {"TimeUTC": "2026-06-24T21:45:00", "TimeDK": "2026-06-24T23:45:00", "PriceArea": "DK1", "DayAheadPriceEUR": 187.740005, "DayAheadPriceDKK": 1403.337763}, {"TimeUTC": "2026-06-24T21:45:00", "TimeDK": "2026-06-24T23:45:00", "PriceArea": "DK2", "DayAheadPriceEUR": 186.050003, "DayAheadPriceDKK": 1390.705167}, {"TimeUTC": "2026-06-24T21:30:00", "TimeDK": "2026-06-24T23:30:00", "PriceArea": "DK1", "DayAheadPriceEUR": 238.470001, "DayAheadPriceDKK": 1782.53941}, {"TimeUTC": "2026-06-24T21:30:00", "TimeDK": "2026-06-24T23:30:00", "PriceArea": "DK2", "DayAheadPriceEUR": 234.179993, "DayAheadPriceDKK": 1750.47203}, {"TimeUTC": "2026-06-24T21:15:00", "TimeDK": "2026-06-24T23:15:00", "PriceArea": "DK1", "DayAheadPriceEUR": 292.859985, "DayAheadPriceDKK": 2189.099102}, {"TimeUTC": "2026-06-24T21:15:00", "TimeDK": "2026-06-24T23:15:00", "PriceArea": "DK2", "DayAheadPriceEUR": 287.589996, "DayAheadPriceDKK": 2149.706461}, {"TimeUTC": "2026-06-24T21:00:00", "TimeDK": "2026-06-24T23:00:00", "PriceArea": "DK1", "DayAheadPriceEUR": 361.950012, "DayAheadPriceDKK": 2705.540145}, {"TimeUTC": "2026-06-24T21:00:00", "TimeDK": "2026-06-24T23:00:00", "PriceArea": "DK2", "DayAheadPriceEUR": 355.429993, "DayAheadPriceDKK": 2656.803655}, {"TimeUTC": "2026-06-24T20:45:00", "TimeDK": "2026-06-24T22:45:00", "PriceArea": "DK1", "DayAheadPriceEUR": 312.01001, "DayAheadPriceDKK": 2332.243624}, {"TimeUTC": "2026-06-24T20:45:00", "TimeDK": "2026-06-24T22:45:00", "PriceArea": "DK2", "DayAheadPriceEUR": 307.790009, "DayAheadPriceDKK": 2300.699538}, {"TimeUTC": "2026-06-24T20:30:00", "TimeDK": "2026-06-24T22:30:00", "PriceArea": "DK1", "DayAheadPriceEUR": 423.799988, "DayAheadPriceDKK": 3167.86253}, {"TimeUTC": "2026-06-24T20:30:00", "TimeDK": "2026-06-24T22:30:00", "PriceArea": "DK2", "DayAheadPriceEUR": 414.779999, "DayAheadPriceDKK": 3100.439015}, {"TimeUTC": "2026-06-24T20:15:00", "TimeDK": "2026-06-24T22:15:00", "PriceArea": "DK1", "DayAheadPriceEUR": 535.219971, "DayAheadPriceDKK": 4000.715761}, {"TimeUTC": "2026-06-24T20:15:00", "TimeDK": "2026-06-24T22:15:00", "PriceArea": "DK2", "DayAheadPriceEUR": 525.590027, "DayAheadPriceDKK": 3928.732893}, {"TimeUTC": "2026-06-24T20:00:00", "TimeDK": "2026-06-24T22:00:00", "PriceArea": "DK1", "DayAheadPriceEUR": 665.460022, "DayAheadPriceDKK": 4974.247118}, {"TimeUTC": "2026-06-24T20:00:00", "TimeDK": "2026-06-24T22:00:00", "PriceArea": "DK2", "DayAheadPriceEUR": 653.47998, "DayAheadPriceDKK": 4884.697503}, {"TimeUTC": "2026-06-24T19:45:00", "TimeDK": "2026-06-24T21:45:00", "PriceArea": "DK1", "DayAheadPriceEUR": 647.929993, "DayAheadPriceDKK": 4843.211905}, {"TimeUTC": "2026-06-24T19:45:00", "TimeDK": "2026-06-24T21:45:00", "PriceArea": "DK2", "DayAheadPriceEUR": 636.27002, "DayAheadPriceDKK": 4756.054772}, {"TimeUTC": "2026-06-24T19:30:00", "TimeDK": "2026-06-24T21:30:00", "PriceArea": "DK1", "DayAheadPriceEUR": 683.440002, "DayAheadPriceDKK": 5108.645671}, {"TimeUTC": "2026-06-24T19:30:00", "TimeDK": "2026-06-24T21:30:00", "PriceArea": "DK2", "DayAheadPriceEUR": 671.130005, "DayAheadPriceDKK": 5016.629674}, {"TimeUTC": "2026-06-24T19:15:00", "TimeDK": "2026-06-24T21:15:00", "PriceArea": "DK1", "DayAheadPriceEUR": 714.48999, "DayAheadPriceDKK": 5340.741226}, {"TimeUTC": "2026-06-24T19:15:00", "TimeDK": "2026-06-24T21:15:00", "PriceArea": "DK2", "DayAheadPriceEUR": 701.619995, "DayAheadPriceDKK": 5244.539301}, {"TimeUTC": "2026-06-24T19:00:00", "TimeDK": "2026-06-24T21:00:00", "PriceArea": "DK1", "DayAheadPriceEUR": 726.619995, "DayAheadPriceDKK": 5431.411801}, {"TimeUTC": "2026-06-24T19:00:00", "TimeDK": "2026-06-24T21:00:00", "PriceArea": "DK2", "DayAheadPriceEUR": 713.539978, "DayAheadPriceDKK": 5333.639982}, {"TimeUTC": "2026-06-24T18:45:00", "TimeDK": "2026-06-24T20:45:00", "PriceArea": "DK1", "DayAheadPriceEUR": 786.830017, "DayAheadPriceDKK": 5881.475694}, {"TimeUTC": "2026-06-24T18:45:00", "TimeDK": "2026-06-24T20:45:00", "PriceArea": "DK2", "DayAheadPriceEUR": 772.659973, "DayAheadPriceDKK": 5775.556032}, {"TimeUTC": "2026-06-24T18:30:00", "TimeDK": "2026-06-24T20:30:00", "PriceArea": "DK1", "DayAheadPriceEUR": 734.090027, "DayAheadPriceDKK": 5487.249543}, {"TimeUTC": "2026-06-24T18:30:00", "TimeDK": "2026-06-24T20:30:00", "PriceArea": "DK2", "DayAheadPriceEUR": 720.869995, "DayAheadPriceDKK": 5388.431126}, {"TimeUTC": "2026-06-24T18:15:00", "TimeDK": "2026-06-24T20:15:00", "PriceArea": "DK1", "DayAheadPriceEUR": 677.869995, "DayAheadPriceDKK": 5067.010426}, {"TimeUTC": "2026-06-24T18:15:00", "TimeDK": "2026-06-24T20:15:00", "PriceArea": "DK2", "DayAheadPriceEUR": 665.659973, "DayAheadPriceDKK": 4975.741732}, {"TimeUTC": "2026-06-24T18:00:00", "TimeDK": "2026-06-24T20:00:00", "PriceArea": "DK1", "DayAheadPriceEUR": 585.369995, "DayAheadPriceDKK": 4375.582176}, {"TimeUTC": "2026-06-24T18:00:00", "TimeDK": "2026-06-24T20:00:00", "PriceArea": "DK2", "DayAheadPriceEUR": 574.830017, "DayAheadPriceDKK": 4296.796894}, {"TimeUTC": "2026-06-24T17:45:00", "TimeDK": "2026-06-24T19:45:00", "PriceArea": "DK1", "DayAheadPriceEUR": 722.780029, "DayAheadPriceDKK": 5402.708439}, {"TimeUTC": "2026-06-24T17:45:00", "TimeDK": "2026-06-24T19:45:00", "PriceArea": "DK2", "DayAheadPriceEUR": 709.039978, "DayAheadPriceDKK": 5300.002932}, {"TimeUTC": "2026-06-24T17:30:00", "TimeDK": "2026-06-24T19:30:00", "PriceArea": "DK1", "DayAheadPriceEUR": 588.960022, "DayAheadPriceDKK": 4402.417268}, {"TimeUTC": "2026-06-24T17:30:00", "TimeDK": "2026-06-24T19:30:00", "PriceArea": "DK2", "DayAheadPriceEUR": 574.890015, "DayAheadPriceDKK": 4297.245373}, {"TimeUTC": "2026-06-24T17:15:00", "TimeDK": "2026-06-24T19:15:00", "PriceArea": "DK1", "DayAheadPriceEUR": 318.850006, "DayAheadPriceDKK": 2383.37191}, {"TimeUTC": "2026-06-24T17:15:00", "TimeDK": "2026-06-24T19:15:00", "PriceArea": "DK2", "DayAheadPriceEUR": 316.570007, "DayAheadPriceDKK": 2366.329145}, {"TimeUTC": "2026-06-24T17:00:00", "TimeDK": "2026-06-24T19:00:00", "PriceArea": "DK1", "DayAheadPriceEUR": 240.0, "DayAheadPriceDKK": 1793.976}, {"TimeUTC": "2026-06-24T17:00:00", "TimeDK": "2026-06-24T19:00:00", "PriceArea": "DK2", "DayAheadPriceEUR": 239.990005, "DayAheadPriceDKK": 1793.901288}], "opdateret": "2026-06-24T22:56:16.559973Z"}